pybna/__init__.py
pybna/_version.py
pybna/conf.py
pybna/config.yaml
pybna/config_testing.yaml
pybna/connectivity.py
pybna/core.py
pybna/dbutils.py
pybna/destinationcategory.py
pybna/destinationosmhandler.py
pybna/destinations.py
pybna/importer.py
pybna/pybna.py
pybna/stress.py
pybna/tests.py
pybna/sql/travel_shed.sql
pybna/sql/travel_shed_composite.sql
pybna/sql/aggregate/01_make_table.sql
pybna/sql/aggregate/05_block_multipliers.sql
pybna/sql/aggregate/10_add_column.sql
pybna/sql/aggregate/15_aggregate.sql
pybna/sql/build_network/cleanup.sql
pybna/sql/build_network/create_tables.sql
pybna/sql/build_network/insert_edges.sql
pybna/sql/build_network/insert_nodes.sql
pybna/sql/connectivity/create_table.sql
pybna/sql/connectivity/link_query.sql
pybna/sql/connectivity/calculation/10_filter_this_block.sql
pybna/sql/connectivity/calculation/15_filter_other_blocks.sql
pybna/sql/connectivity/calculation/17_remove_ls_connections_for_scenario.sql
pybna/sql/connectivity/calculation/20_assign_nodes_to_blocks.sql
pybna/sql/connectivity/calculation/25_flip_low_stress.sql
pybna/sql/connectivity/calculation/30_network_subset.sql
pybna/sql/connectivity/calculation/35_this_block_nodes.sql
pybna/sql/connectivity/calculation/40_distance_table.sql
pybna/sql/connectivity/calculation/60_cost_to_blocks.sql
pybna/sql/connectivity/calculation/70_combine_cost_matrices.sql
pybna/sql/connectivity/calculation/80_insert.sql
pybna/sql/connectivity/calculation/80_insert_with_scenario.sql
pybna/sql/connectivity/scenarios/get_affected_block_ids.sql
pybna/sql/connectivity/scenarios/get_affected_road_ids.sql
pybna/sql/connectivity/scenarios/get_affected_road_ids_subtract.sql
pybna/sql/destinations/02_count_based_score.sql
pybna/sql/destinations/02_percentage_based_score.sql
pybna/sql/destinations/03_combine_counts.sql
pybna/sql/destinations/04_all_combined.sql
pybna/sql/destinations/05_add_geoms.sql
pybna/sql/importer/process_destinations.sql
pybna/sql/importer/intersections/05_standardize_osm.sql
pybna-1.0.1.dist-info/METADATA
pybna-1.0.1.dist-info/WHEEL
pybna-1.0.1.dist-info/top_level.txt
pybna-1.0.1.dist-info/RECORD
