Metadata-Version: 2.1
Name: pybna
Version: 1.0.1
Summary: A library for measuring bike network connectivity using PeopleForBikes' Bicycle Network Analysis methodology
Home-page: https://github.com/tooledesign/pybna
Author: Spencer Gardner
License: UNKNOWN
Platform: UNKNOWN
Requires-Dist: PyYAML
Requires-Dist: geopandas
Requires-Dist: munch
Requires-Dist: osmnx
Requires-Dist: overpass
Requires-Dist: pandas
Requires-Dist: psycopg2-binary
Requires-Dist: tqdm
Requires-Dist: xlrd
